dis_cover/__init__.py
dis_cover/__version__.py
dis_cover/analysis/__init__.py
dis_cover/analysis/analysis.py
dis_cover/cli/__init__.py
dis_cover/cli/__main__.py
dis_cover/cli/cli.py
dis_cover/reconstruction/__init__.py
dis_cover/reconstruction/reconstruction.py
dis_cover-1.0.0.dist-info/LICENSE
dis_cover-1.0.0.dist-info/METADATA
dis_cover-1.0.0.dist-info/WHEEL
dis_cover-1.0.0.dist-info/entry_points.txt
dis_cover-1.0.0.dist-info/top_level.txt
dis_cover-1.0.0.dist-info/RECORD
