Metadata-Version: 2.1
Name: dis-cover
Version: 1.0.0
Summary: Disasemble binaries and recover as much info as possible.
Home-page: https://github.com/hexhive/dis-cover
Author: Louis Merlin
Author-email: hello@louismerl.in
License: MIT
Platform: UNKNOWN
Classifier: License :: OSI Approved :: MIT License
Classifier: Programming Language :: Python
Classifier: Programming Language :: Python :: 3
Classifier: Programming Language :: Python :: 3.6
Classifier: Programming Language :: Python :: Implementation :: CPython
Classifier: Programming Language :: Python :: Implementation :: PyPy
Requires-Python: >=3.6.0
Requires-Dist: itanium-demangler (>=1.0)
Requires-Dist: pyelftools (>=0.27)
